pydantic_sqs/__init__.py
pydantic_sqs/abstract.py
pydantic_sqs/exceptions.py
pydantic_sqs/model.py
pydantic_sqs/queue.py
pydantic_sqs-0.2.0.dist-info/LICENSE
pydantic_sqs-0.2.0.dist-info/WHEEL
pydantic_sqs-0.2.0.dist-info/METADATA
pydantic_sqs-0.2.0.dist-info/RECORD
