Metadata-Version: 2.1
Name: pydantic-sqs
Version: 0.2.0
Summary: Send and receive AWS SQS messages directly to pydantic objects
Home-page: https://github.com/andrewthetechie/pydantic-sqs
License: MIT
Author: Andrew Herrington
Author-email: andrew.the.techie@gmail.com
Requires-Python: >=3.7,<4.0
Classifier: Development Status :: 4 - Beta
Classifier: Framework :: AsyncIO
Classifier: Intended Audience :: Developers
Classifier: License :: OSI Approved :: MIT License
Classifier: Programming Language :: Python
Classifier: Programming Language :: Python :: 3
Classifier: Programming Language :: Python :: 3.7
Classifier: Programming Language :: Python :: 3.8
Classifier: Programming Language :: Python :: 3.9
Classifier: Programming Language :: Python :: 3.10
Classifier: Programming Language :: Python :: 3.11
Classifier: Programming Language :: Python :: 3
Classifier: Programming Language :: Python :: 3.10
Classifier: Programming Language :: Python :: 3.7
Classifier: Programming Language :: Python :: 3.8
Classifier: Programming Language :: Python :: 3.9
Requires-Dist: aiobotocore (>=2.4.0,<3.0.0)
Requires-Dist: pydantic (>=1.10.0,<2.0.0)
Project-URL: Changelog, https://github.com/andrewthetechie/pydantic-sqs/releases
Project-URL: Documentation, https://pydantic-sqs.readthedocs.io/en/latest/
Project-URL: Repository, https://github.com/andrewthetechie/pydantic-sqs
